{
  "updated_at": "2026-07-07T22:46:58.750519+00:00",
  "signals": [
    {
      "ticker": "AAPL",
      "action": "ACHAT",
      "prix": 310.66,
      "raisons": [
        "Tendance haussière confirmée, momentum en accélération",
        "RSI à 60 (marge avant surachat)"
      ],
      "indicateurs": {
        "sma20": 295.04,
        "sma50": 295.0,
        "rsi": 59.5,
        "macd_histogramme": 2.008,
        "atr": 8.82
      },
      "stop_loss_suggere": 293.01,
      "take_profit_suggere": 337.13,
      "horodatage": "2026-07-07T22:46:41.282089+00:00"
    },
    {
      "ticker": "MSFT",
      "action": "ATTENTE",
      "prix": 388.84,
      "raisons": [
        "Aucun signal fort détecté — tendance et momentum ne sont pas alignés"
      ],
      "indicateurs": {
        "sma20": 383.5,
        "sma50": 405.79,
        "rsi": 45.2,
        "macd_histogramme": 2.437,
        "atr": 13.0
      },
      "stop_loss_suggere": null,
      "take_profit_suggere": null,
      "horodatage": "2026-07-07T22:46:41.953441+00:00"
    },
    {
      "ticker": "GOOGL",
      "action": "ATTENTE",
      "prix": 367.03,
      "raisons": [
        "Aucun signal fort détecté — tendance et momentum ne sont pas alignés"
      ],
      "indicateurs": {
        "sma20": 358.18,
        "sma50": 371.94,
        "rsi": 48.6,
        "macd_histogramme": 1.826,
        "atr": 11.78
      },
      "stop_loss_suggere": null,
      "take_profit_suggere": null,
      "horodatage": "2026-07-07T22:46:42.574293+00:00"
    },
    {
      "ticker": "AMZN",
      "action": "ATTENTE",
      "prix": 245.98,
      "raisons": [
        "Aucun signal fort détecté — tendance et momentum ne sont pas alignés"
      ],
      "indicateurs": {
        "sma20": 239.76,
        "sma50": 255.01,
        "rsi": 50.0,
        "macd_histogramme": 1.62,
        "atr": 8.23
      },
      "stop_loss_suggere": null,
      "take_profit_suggere": null,
      "horodatage": "2026-07-07T22:46:43.183318+00:00"
    },
    {
      "ticker": "NVDA",
      "action": "ATTENTE",
      "prix": 196.93,
      "raisons": [
        "Aucun signal fort détecté — tendance et momentum ne sont pas alignés"
      ],
      "indicateurs": {
        "sma20": 201.92,
        "sma50": 209.6,
        "rsi": 33.5,
        "macd_histogramme": -0.571,
        "atr": 6.32
      },
      "stop_loss_suggere": null,
      "take_profit_suggere": null,
      "horodatage": "2026-07-07T22:46:43.839814+00:00"
    },
    {
      "ticker": "META",
      "action": "ACHAT",
      "prix": 615.58,
      "raisons": [
        "Tendance haussière confirmée, momentum en accélération",
        "RSI à 55 (marge avant surachat)"
      ],
      "indicateurs": {
        "sma20": 576.33,
        "sma50": 602.47,
        "rsi": 55.1,
        "macd_histogramme": 6.701,
        "atr": 22.86
      },
      "stop_loss_suggere": 569.85,
      "take_profit_suggere": 684.18,
      "horodatage": "2026-07-07T22:46:44.458277+00:00"
    },
    {
      "ticker": "TSLA",
      "action": "ATTENTE",
      "prix": 402.9,
      "raisons": [
        "Aucun signal fort détecté — tendance et momentum ne sont pas alignés"
      ],
      "indicateurs": {
        "sma20": 399.82,
        "sma50": 407.65,
        "rsi": 47.7,
        "macd_histogramme": 1.984,
        "atr": 20.33
      },
      "stop_loss_suggere": null,
      "take_profit_suggere": null,
      "horodatage": "2026-07-07T22:46:45.090193+00:00"
    },
    {
      "ticker": "JPM",
      "action": "ATTENTE",
      "prix": 339.22,
      "raisons": [
        "Aucun signal fort détecté — tendance et momentum ne sont pas alignés"
      ],
      "indicateurs": {
        "sma20": 325.78,
        "sma50": 312.31,
        "rsi": 69.2,
        "macd_histogramme": 0.559,
        "atr": 7.91
      },
      "stop_loss_suggere": null,
      "take_profit_suggere": null,
      "horodatage": "2026-07-07T22:46:45.799445+00:00"
    },
    {
      "ticker": "V",
      "action": "ATTENTE",
      "prix": 352.2,
      "raisons": [
        "Aucun signal fort détecté — tendance et momentum ne sont pas alignés"
      ],
      "indicateurs": {
        "sma20": 334.26,
        "sma50": 327.6,
        "rsi": 71.9,
        "macd_histogramme": 2.756,
        "atr": 8.92
      },
      "stop_loss_suggere": null,
      "take_profit_suggere": null,
      "horodatage": "2026-07-07T22:46:46.465802+00:00"
    },
    {
      "ticker": "JNJ",
      "action": "ATTENTE",
      "prix": 267.24,
      "raisons": [
        "Aucun signal fort détecté — tendance et momentum ne sont pas alignés"
      ],
      "indicateurs": {
        "sma20": 244.36,
        "sma50": 233.59,
        "rsi": 75.2,
        "macd_histogramme": 2.466,
        "atr": 6.69
      },
      "stop_loss_suggere": null,
      "take_profit_suggere": null,
      "horodatage": "2026-07-07T22:46:47.275560+00:00"
    },
    {
      "ticker": "WMT",
      "action": "ATTENTE",
      "prix": 111.54,
      "raisons": [
        "Aucun signal fort détecté — tendance et momentum ne sont pas alignés"
      ],
      "indicateurs": {
        "sma20": 116.79,
        "sma50": 122.16,
        "rsi": 28.9,
        "macd_histogramme": -0.479,
        "atr": 2.95
      },
      "stop_loss_suggere": null,
      "take_profit_suggere": null,
      "horodatage": "2026-07-07T22:46:48.110470+00:00"
    },
    {
      "ticker": "PG",
      "action": "ACHAT",
      "prix": 152.75,
      "raisons": [
        "Tendance haussière confirmée, momentum en accélération",
        "RSI à 54 (marge avant surachat)"
      ],
      "indicateurs": {
        "sma20": 149.44,
        "sma50": 146.41,
        "rsi": 54.1,
        "macd_histogramme": 0.048,
        "atr": 3.24
      },
      "stop_loss_suggere": 146.27,
      "take_profit_suggere": 162.47,
      "horodatage": "2026-07-07T22:46:48.927881+00:00"
    },
    {
      "ticker": "MA",
      "action": "ATTENTE",
      "prix": 531.62,
      "raisons": [
        "Aucun signal fort détecté — tendance et momentum ne sont pas alignés"
      ],
      "indicateurs": {
        "sma20": 501.28,
        "sma50": 498.49,
        "rsi": 70.1,
        "macd_histogramme": 5.133,
        "atr": 13.27
      },
      "stop_loss_suggere": null,
      "take_profit_suggere": null,
      "horodatage": "2026-07-07T22:46:49.618568+00:00"
    },
    {
      "ticker": "HD",
      "action": "ACHAT",
      "prix": 345.21,
      "raisons": [
        "Tendance haussière confirmée, momentum en accélération",
        "RSI à 59 (marge avant surachat)"
      ],
      "indicateurs": {
        "sma20": 336.45,
        "sma50": 323.62,
        "rsi": 59.2,
        "macd_histogramme": 1.252,
        "atr": 9.5
      },
      "stop_loss_suggere": 326.22,
      "take_profit_suggere": 373.7,
      "horodatage": "2026-07-07T22:46:50.330728+00:00"
    },
    {
      "ticker": "DIS",
      "action": "VENTE",
      "prix": 97.48,
      "raisons": [
        "Tendance baissière confirmée, momentum en accélération à la baisse"
      ],
      "indicateurs": {
        "sma20": 99.12,
        "sma50": 101.13,
        "rsi": 41.7,
        "macd_histogramme": -0.172,
        "atr": 2.48
      },
      "stop_loss_suggere": null,
      "take_profit_suggere": null,
      "horodatage": "2026-07-07T22:46:51.085792+00:00"
    },
    {
      "ticker": "BAC",
      "action": "ATTENTE",
      "prix": 59.86,
      "raisons": [
        "Aucun signal fort détecté — tendance et momentum ne sont pas alignés"
      ],
      "indicateurs": {
        "sma20": 57.0,
        "sma50": 53.78,
        "rsi": 74.5,
        "macd_histogramme": 0.137,
        "atr": 1.2
      },
      "stop_loss_suggere": null,
      "take_profit_suggere": null,
      "horodatage": "2026-07-07T22:46:51.814026+00:00"
    },
    {
      "ticker": "XOM",
      "action": "ATTENTE",
      "prix": 141.69,
      "raisons": [
        "Aucun signal fort détecté — tendance et momentum ne sont pas alignés"
      ],
      "indicateurs": {
        "sma20": 140.98,
        "sma50": 147.15,
        "rsi": 52.0,
        "macd_histogramme": 0.311,
        "atr": 2.66
      },
      "stop_loss_suggere": null,
      "take_profit_suggere": null,
      "horodatage": "2026-07-07T22:46:52.589574+00:00"
    },
    {
      "ticker": "PFE",
      "action": "ATTENTE",
      "prix": 24.07,
      "raisons": [
        "Aucun signal fort détecté — tendance et momentum ne sont pas alignés"
      ],
      "indicateurs": {
        "sma20": 24.94,
        "sma50": 25.51,
        "rsi": 30.7,
        "macd_histogramme": -0.081,
        "atr": 0.64
      },
      "stop_loss_suggere": null,
      "take_profit_suggere": null,
      "horodatage": "2026-07-07T22:46:53.339711+00:00"
    },
    {
      "ticker": "KO",
      "action": "ATTENTE",
      "prix": 84.05,
      "raisons": [
        "Aucun signal fort détecté — tendance et momentum ne sont pas alignés"
      ],
      "indicateurs": {
        "sma20": 81.37,
        "sma50": 79.85,
        "rsi": 63.5,
        "macd_histogramme": 0.265,
        "atr": 1.71
      },
      "stop_loss_suggere": null,
      "take_profit_suggere": null,
      "horodatage": "2026-07-07T22:46:54.112296+00:00"
    },
    {
      "ticker": "NFLX",
      "action": "ATTENTE",
      "prix": 76.18,
      "raisons": [
        "Aucun signal fort détecté — tendance et momentum ne sont pas alignés"
      ],
      "indicateurs": {
        "sma20": 76.69,
        "sma50": 83.44,
        "rsi": 39.0,
        "macd_histogramme": 0.621,
        "atr": 2.86
      },
      "stop_loss_suggere": null,
      "take_profit_suggere": null,
      "horodatage": "2026-07-07T22:46:54.742266+00:00"
    },
    {
      "ticker": "ADBE",
      "action": "ATTENTE",
      "prix": 221.54,
      "raisons": [
        "Aucun signal fort détecté — tendance et momentum ne sont pas alignés"
      ],
      "indicateurs": {
        "sma20": 210.55,
        "sma50": 233.82,
        "rsi": 64.0,
        "macd_histogramme": 3.439,
        "atr": 8.27
      },
      "stop_loss_suggere": null,
      "take_profit_suggere": null,
      "horodatage": "2026-07-07T22:46:55.420180+00:00"
    },
    {
      "ticker": "CRM",
      "action": "ATTENTE",
      "prix": 169.52,
      "raisons": [
        "Aucun signal fort détecté — tendance et momentum ne sont pas alignés"
      ],
      "indicateurs": {
        "sma20": 161.84,
        "sma50": 173.53,
        "rsi": 55.6,
        "macd_histogramme": 1.929,
        "atr": 6.12
      },
      "stop_loss_suggere": null,
      "take_profit_suggere": null,
      "horodatage": "2026-07-07T22:46:56.061713+00:00"
    },
    {
      "ticker": "INTC",
      "action": "ATTENTE",
      "prix": 110.39,
      "raisons": [
        "Aucun signal fort détecté — tendance et momentum ne sont pas alignés"
      ],
      "indicateurs": {
        "sma20": 124.21,
        "sma50": 115.39,
        "rsi": 40.7,
        "macd_histogramme": -2.539,
        "atr": 11.24
      },
      "stop_loss_suggere": null,
      "take_profit_suggere": null,
      "horodatage": "2026-07-07T22:46:56.729324+00:00"
    },
    {
      "ticker": "CSCO",
      "action": "ATTENTE",
      "prix": 111.79,
      "raisons": [
        "Aucun signal fort détecté — tendance et momentum ne sont pas alignés"
      ],
      "indicateurs": {
        "sma20": 118.03,
        "sma50": 111.57,
        "rsi": 35.6,
        "macd_histogramme": -1.492,
        "atr": 3.47
      },
      "stop_loss_suggere": null,
      "take_profit_suggere": null,
      "horodatage": "2026-07-07T22:46:57.429986+00:00"
    },
    {
      "ticker": "PEP",
      "action": "ATTENTE",
      "prix": 144.98,
      "raisons": [
        "Aucun signal fort détecté — tendance et momentum ne sont pas alignés"
      ],
      "indicateurs": {
        "sma20": 142.27,
        "sma50": 146.08,
        "rsi": 47.9,
        "macd_histogramme": 0.622,
        "atr": 3.61
      },
      "stop_loss_suggere": null,
      "take_profit_suggere": null,
      "horodatage": "2026-07-07T22:46:58.250266+00:00"
    }
  ]
}