{
  "updated_at": "2026-06-29T19:25:35.867395+00:00",
  "signals": [
    {
      "ticker": "AAPL",
      "action": "ATTENTE",
      "prix": 282.54,
      "raisons": [
        "Aucun signal fort détecté — tendance et momentum ne sont pas alignés"
      ],
      "indicateurs": {
        "sma20": 296.81,
        "sma50": 291.8,
        "rsi": 35.8,
        "macd_histogramme": -2.695,
        "atr": 8.67
      },
      "stop_loss_suggere": null,
      "take_profit_suggere": null,
      "horodatage": "2026-06-29T19:25:17.031313+00:00"
    },
    {
      "ticker": "MSFT",
      "action": "ATTENTE",
      "prix": 367.83,
      "raisons": [
        "Aucun signal fort détecté — tendance et momentum ne sont pas alignés"
      ],
      "indicateurs": {
        "sma20": 395.99,
        "sma50": 409.49,
        "rsi": 31.3,
        "macd_histogramme": -3.254,
        "atr": 13.0
      },
      "stop_loss_suggere": null,
      "take_profit_suggere": null,
      "horodatage": "2026-06-29T19:25:17.806571+00:00"
    },
    {
      "ticker": "GOOGL",
      "action": "VENTE",
      "prix": 352.34,
      "raisons": [
        "Tendance baissière confirmée, momentum en accélération à la baisse"
      ],
      "indicateurs": {
        "sma20": 359.36,
        "sma50": 369.45,
        "rsi": 43.5,
        "macd_histogramme": -2.263,
        "atr": 13.29
      },
      "stop_loss_suggere": null,
      "take_profit_suggere": null,
      "horodatage": "2026-06-29T19:25:18.448742+00:00"
    },
    {
      "ticker": "AMZN",
      "action": "VENTE",
      "prix": 240.49,
      "raisons": [
        "Tendance baissière confirmée, momentum en accélération à la baisse"
      ],
      "indicateurs": {
        "sma20": 242.52,
        "sma50": 255.94,
        "rsi": 46.6,
        "macd_histogramme": -0.558,
        "atr": 9.04
      },
      "stop_loss_suggere": null,
      "take_profit_suggere": null,
      "horodatage": "2026-06-29T19:25:19.160101+00:00"
    },
    {
      "ticker": "NVDA",
      "action": "ATTENTE",
      "prix": 194.75,
      "raisons": [
        "Aucun signal fort détecté — tendance et momentum ne sont pas alignés"
      ],
      "indicateurs": {
        "sma20": 206.91,
        "sma50": 209.85,
        "rsi": 37.2,
        "macd_histogramme": -1.828,
        "atr": 6.8
      },
      "stop_loss_suggere": null,
      "take_profit_suggere": null,
      "horodatage": "2026-06-29T19:25:19.915641+00:00"
    },
    {
      "ticker": "META",
      "action": "VENTE",
      "prix": 565.21,
      "raisons": [
        "Tendance baissière confirmée, momentum en accélération à la baisse"
      ],
      "indicateurs": {
        "sma20": 579.65,
        "sma50": 610.2,
        "rsi": 43.5,
        "macd_histogramme": -1.676,
        "atr": 18.86
      },
      "stop_loss_suggere": null,
      "take_profit_suggere": null,
      "horodatage": "2026-06-29T19:25:20.694487+00:00"
    },
    {
      "ticker": "TSLA",
      "action": "ATTENTE",
      "prix": 412.18,
      "raisons": [
        "Aucun signal fort détecté — tendance et momentum ne sont pas alignés"
      ],
      "indicateurs": {
        "sma20": 400.37,
        "sma50": 405.23,
        "rsi": 51.1,
        "macd_histogramme": -1.109,
        "atr": 18.59
      },
      "stop_loss_suggere": null,
      "take_profit_suggere": null,
      "horodatage": "2026-06-29T19:25:21.294974+00:00"
    },
    {
      "ticker": "JPM",
      "action": "ATTENTE",
      "prix": 330.59,
      "raisons": [
        "Aucun signal fort détecté — tendance et momentum ne sont pas alignés"
      ],
      "indicateurs": {
        "sma20": 319.59,
        "sma50": 311.52,
        "rsi": 66.4,
        "macd_histogramme": 0.912,
        "atr": 7.95
      },
      "stop_loss_suggere": null,
      "take_profit_suggere": null,
      "horodatage": "2026-06-29T19:25:22.018221+00:00"
    },
    {
      "ticker": "V",
      "action": "ATTENTE",
      "prix": 342.58,
      "raisons": [
        "Aucun signal fort détecté — tendance et momentum ne sont pas alignés"
      ],
      "indicateurs": {
        "sma20": 325.83,
        "sma50": 323.46,
        "rsi": 72.3,
        "macd_histogramme": 1.447,
        "atr": 7.26
      },
      "stop_loss_suggere": null,
      "take_profit_suggere": null,
      "horodatage": "2026-06-29T19:25:22.781221+00:00"
    },
    {
      "ticker": "JNJ",
      "action": "ATTENTE",
      "prix": 257.44,
      "raisons": [
        "Aucun signal fort détecté — tendance et momentum ne sont pas alignés"
      ],
      "indicateurs": {
        "sma20": 235.96,
        "sma50": 230.44,
        "rsi": 75.0,
        "macd_histogramme": 2.286,
        "atr": 5.87
      },
      "stop_loss_suggere": null,
      "take_profit_suggere": null,
      "horodatage": "2026-06-29T19:25:23.630632+00:00"
    },
    {
      "ticker": "WMT",
      "action": "ATTENTE",
      "prix": 114.67,
      "raisons": [
        "Aucun signal fort détecté — tendance et momentum ne sont pas alignés"
      ],
      "indicateurs": {
        "sma20": 118.05,
        "sma50": 123.96,
        "rsi": 32.3,
        "macd_histogramme": -0.123,
        "atr": 2.67
      },
      "stop_loss_suggere": null,
      "take_profit_suggere": null,
      "horodatage": "2026-06-29T19:25:24.399736+00:00"
    },
    {
      "ticker": "PG",
      "action": "ATTENTE",
      "prix": 147.95,
      "raisons": [
        "Aucun signal fort détecté — tendance et momentum ne sont pas alignés"
      ],
      "indicateurs": {
        "sma20": 147.47,
        "sma50": 145.78,
        "rsi": 56.2,
        "macd_histogramme": -0.112,
        "atr": 2.84
      },
      "stop_loss_suggere": null,
      "take_profit_suggere": null,
      "horodatage": "2026-06-29T19:25:25.199470+00:00"
    },
    {
      "ticker": "MA",
      "action": "ATTENTE",
      "prix": 512.52,
      "raisons": [
        "Aucun signal fort détecté — tendance et momentum ne sont pas alignés"
      ],
      "indicateurs": {
        "sma20": 490.28,
        "sma50": 496.98,
        "rsi": 65.0,
        "macd_histogramme": 2.254,
        "atr": 11.39
      },
      "stop_loss_suggere": null,
      "take_profit_suggere": null,
      "horodatage": "2026-06-29T19:25:25.862937+00:00"
    },
    {
      "ticker": "HD",
      "action": "ATTENTE",
      "prix": 349.9,
      "raisons": [
        "Aucun signal fort détecté — tendance et momentum ne sont pas alignés"
      ],
      "indicateurs": {
        "sma20": 325.98,
        "sma50": 321.37,
        "rsi": 74.0,
        "macd_histogramme": 2.918,
        "atr": 9.07
      },
      "stop_loss_suggere": null,
      "take_profit_suggere": null,
      "horodatage": "2026-06-29T19:25:26.714311+00:00"
    },
    {
      "ticker": "DIS",
      "action": "VENTE",
      "prix": 98.77,
      "raisons": [
        "Tendance baissière confirmée, momentum en accélération à la baisse"
      ],
      "indicateurs": {
        "sma20": 100.52,
        "sma50": 102.61,
        "rsi": 49.7,
        "macd_histogramme": -0.181,
        "atr": 2.36
      },
      "stop_loss_suggere": null,
      "take_profit_suggere": null,
      "horodatage": "2026-06-29T19:25:27.584495+00:00"
    },
    {
      "ticker": "BAC",
      "action": "ATTENTE",
      "prix": 58.03,
      "raisons": [
        "Aucun signal fort détecté — tendance et momentum ne sont pas alignés"
      ],
      "indicateurs": {
        "sma20": 55.48,
        "sma50": 53.22,
        "rsi": 81.6,
        "macd_histogramme": 0.187,
        "atr": 1.17
      },
      "stop_loss_suggere": null,
      "take_profit_suggere": null,
      "horodatage": "2026-06-29T19:25:28.439279+00:00"
    },
    {
      "ticker": "XOM",
      "action": "ATTENTE",
      "prix": 136.27,
      "raisons": [
        "Aucun signal fort détecté — tendance et momentum ne sont pas alignés"
      ],
      "indicateurs": {
        "sma20": 144.26,
        "sma50": 148.14,
        "rsi": 21.1,
        "macd_histogramme": -0.761,
        "atr": 3.61
      },
      "stop_loss_suggere": null,
      "take_profit_suggere": null,
      "horodatage": "2026-06-29T19:25:29.323248+00:00"
    },
    {
      "ticker": "PFE",
      "action": "ATTENTE",
      "prix": 24.35,
      "raisons": [
        "Aucun signal fort détecté — tendance et momentum ne sont pas alignés"
      ],
      "indicateurs": {
        "sma20": 25.34,
        "sma50": 25.78,
        "rsi": 34.6,
        "macd_histogramme": -0.168,
        "atr": 0.58
      },
      "stop_loss_suggere": null,
      "take_profit_suggere": null,
      "horodatage": "2026-06-29T19:25:30.168315+00:00"
    },
    {
      "ticker": "KO",
      "action": "ATTENTE",
      "prix": 82.52,
      "raisons": [
        "Aucun signal fort détecté — tendance et momentum ne sont pas alignés"
      ],
      "indicateurs": {
        "sma20": 80.16,
        "sma50": 79.06,
        "rsi": 65.1,
        "macd_histogramme": 0.136,
        "atr": 1.62
      },
      "stop_loss_suggere": null,
      "take_profit_suggere": null,
      "horodatage": "2026-06-29T19:25:31.004946+00:00"
    },
    {
      "ticker": "NFLX",
      "action": "ATTENTE",
      "prix": 73.97,
      "raisons": [
        "Aucun signal fort détecté — tendance et momentum ne sont pas alignés"
      ],
      "indicateurs": {
        "sma20": 78.65,
        "sma50": 85.35,
        "rsi": 27.8,
        "macd_histogramme": -0.348,
        "atr": 2.49
      },
      "stop_loss_suggere": null,
      "take_profit_suggere": null,
      "horodatage": "2026-06-29T19:25:31.743492+00:00"
    },
    {
      "ticker": "ADBE",
      "action": "ATTENTE",
      "prix": 206.43,
      "raisons": [
        "Aucun signal fort détecté — tendance et momentum ne sont pas alignés"
      ],
      "indicateurs": {
        "sma20": 221.9,
        "sma50": 237.01,
        "rsi": 24.7,
        "macd_histogramme": -0.949,
        "atr": 9.65
      },
      "stop_loss_suggere": null,
      "take_profit_suggere": null,
      "horodatage": "2026-06-29T19:25:32.414966+00:00"
    },
    {
      "ticker": "CRM",
      "action": "ATTENTE",
      "prix": 158.58,
      "raisons": [
        "Aucun signal fort détecté — tendance et momentum ne sont pas alignés"
      ],
      "indicateurs": {
        "sma20": 169.46,
        "sma50": 175.44,
        "rsi": 24.9,
        "macd_histogramme": -0.872,
        "atr": 6.42
      },
      "stop_loss_suggere": null,
      "take_profit_suggere": null,
      "horodatage": "2026-06-29T19:25:33.205664+00:00"
    },
    {
      "ticker": "INTC",
      "action": "ATTENTE",
      "prix": 131.25,
      "raisons": [
        "Aucun signal fort détecté — tendance et momentum ne sont pas alignés"
      ],
      "indicateurs": {
        "sma20": 120.25,
        "sma50": 109.64,
        "rsi": 63.7,
        "macd_histogramme": 0.251,
        "atr": 10.93
      },
      "stop_loss_suggere": null,
      "take_profit_suggere": null,
      "horodatage": "2026-06-29T19:25:33.946259+00:00"
    },
    {
      "ticker": "CSCO",
      "action": "ATTENTE",
      "prix": 117.65,
      "raisons": [
        "Aucun signal fort détecté — tendance et momentum ne sont pas alignés"
      ],
      "indicateurs": {
        "sma20": 121.16,
        "sma50": 109.35,
        "rsi": 38.7,
        "macd_histogramme": -1.528,
        "atr": 3.81
      },
      "stop_loss_suggere": null,
      "take_profit_suggere": null,
      "horodatage": "2026-06-29T19:25:34.615436+00:00"
    },
    {
      "ticker": "PEP",
      "action": "VENTE",
      "prix": 137.87,
      "raisons": [
        "Tendance baissière confirmée, momentum en accélération à la baisse"
      ],
      "indicateurs": {
        "sma20": 141.99,
        "sma50": 147.3,
        "rsi": 43.8,
        "macd_histogramme": -0.113,
        "atr": 2.99
      },
      "stop_loss_suggere": null,
      "take_profit_suggere": null,
      "horodatage": "2026-06-29T19:25:35.367134+00:00"
    }
  ]
}